README.md
setup.py
globomap_plugin_zabbix/__init__.py
globomap_plugin_zabbix/zabbix.py
globomap_plugin_zabbix.egg-info/PKG-INFO
globomap_plugin_zabbix.egg-info/SOURCES.txt
globomap_plugin_zabbix.egg-info/dependency_links.txt
globomap_plugin_zabbix.egg-info/top_level.txt