Metadata-Version: 1.0
Name: globomap-plugin-zabbix
Version: 0.1.4
Summary: Zabbix monitoring plugin on globomap-api
Home-page: https://gitlab.globoi.com/sergios/globomap-plugin-zabbix
Author: Storm
Author-email: storm@corp.globo.com
License: UNKNOWN
Platform: UNKNOWN
